{
	"cmake" : 
	{
		"generator" : 
		{
			"multiConfig" : false,
			"name" : "Unix Makefiles"
		},
		"paths" : 
		{
			"cmake" : "/var/lib/snapd/snap/clion/235/bin/cmake/linux/x64/bin/cmake",
			"cpack" : "/var/lib/snapd/snap/clion/235/bin/cmake/linux/x64/bin/cpack",
			"ctest" : "/var/lib/snapd/snap/clion/235/bin/cmake/linux/x64/bin/ctest",
			"root" : "/var/lib/snapd/snap/clion/235/bin/cmake/linux/x64/share/cmake-3.25"
		},
		"version" : 
		{
			"isDirty" : false,
			"major" : 3,
			"minor" : 25,
			"patch" : 2,
			"string" : "3.25.2",
			"suffix" : ""
		}
	},
	"objects" : 
	[
		{
			"jsonFile" : "codemodel-v2-cd6802dfe7c49d2f3ca3.json",
			"kind" : "codemodel",
			"version" : 
			{
				"major" : 2,
				"minor" : 4
			}
		},
		{
			"jsonFile" : "cache-v2-6ffceae92cbf6170f5dc.json",
			"kind" : "cache",
			"version" : 
			{
				"major" : 2,
				"minor" : 0
			}
		},
		{
			"jsonFile" : "cmakeFiles-v1-73d7c3107486db17cfb7.json",
			"kind" : "cmakeFiles",
			"version" : 
			{
				"major" : 1,
				"minor" : 0
			}
		},
		{
			"jsonFile" : "toolchains-v1-5e864d45b6495c775afc.json",
			"kind" : "toolchains",
			"version" : 
			{
				"major" : 1,
				"minor" : 0
			}
		}
	],
	"reply" : 
	{
		"cache-v2" : 
		{
			"jsonFile" : "cache-v2-6ffceae92cbf6170f5dc.json",
			"kind" : "cache",
			"version" : 
			{
				"major" : 2,
				"minor" : 0
			}
		},
		"cmakeFiles-v1" : 
		{
			"jsonFile" : "cmakeFiles-v1-73d7c3107486db17cfb7.json",
			"kind" : "cmakeFiles",
			"version" : 
			{
				"major" : 1,
				"minor" : 0
			}
		},
		"codemodel-v2" : 
		{
			"jsonFile" : "codemodel-v2-cd6802dfe7c49d2f3ca3.json",
			"kind" : "codemodel",
			"version" : 
			{
				"major" : 2,
				"minor" : 4
			}
		},
		"toolchains-v1" : 
		{
			"jsonFile" : "toolchains-v1-5e864d45b6495c775afc.json",
			"kind" : "toolchains",
			"version" : 
			{
				"major" : 1,
				"minor" : 0
			}
		}
	}
}
